minju210_lotto/__init__.py
minju210_lotto/draw.py
minju210_lotto-0.2.0.dist-info/METADATA
minju210_lotto-0.2.0.dist-info/WHEEL
minju210_lotto-0.2.0.dist-info/top_level.txt
minju210_lotto-0.2.0.dist-info/RECORD
