Metadata-Version: 2.1
Name: minju210_lotto
Version: 0.2.0
Summary: Default template for PDM package
Author-email: minju210 <juliana6190210@gmail.com>
License: MIT
Requires-Python: >=3.9
